mailinator/__init__.py
mailinator/base.py
mailinator/domain.py
mailinator/mailinator.py
mailinator/message.py
mailinator/models.py
mailinator/rules.py
tests/__init__.py
tests/test_mailinator.py
mailinator_python_client_storrellas-0.0.4.dist-info/LICENSE
mailinator_python_client_storrellas-0.0.4.dist-info/METADATA
mailinator_python_client_storrellas-0.0.4.dist-info/WHEEL
mailinator_python_client_storrellas-0.0.4.dist-info/top_level.txt
mailinator_python_client_storrellas-0.0.4.dist-info/RECORD
