Metadata-Version: 2.1
Name: mailinator-python-client-storrellas
Version: 0.0.4
Summary: SDK for Mailinator
Home-page: https://github.com/manybrain/mailinator-python-client
Author: Sergi Torrellas
Author-email: storrellas@gmail.com
License: UNKNOWN
Platform: UNKNOWN
Classifier: Programming Language :: Python :: 3
Classifier: License :: OSI Approved :: MIT License
Classifier: Operating System :: OS Independent
Requires-Python: >=3.6
Requires-Dist: requests
